PyAMQP-0.1.0.7.dist-info/DESCRIPTION.rst
PyAMQP-0.1.0.7.dist-info/METADATA
PyAMQP-0.1.0.7.dist-info/RECORD
PyAMQP-0.1.0.7.dist-info/WHEEL
PyAMQP-0.1.0.7.dist-info/metadata.json
PyAMQP-0.1.0.7.dist-info/top_level.txt
pyamqp/__init__.py
pyamqp/rabbit/__init__.py
pyamqp/rabbit/dispatcher.py
pyamqp/rabbit/receiver.py
pyamqp/rabbit/core/__init__.py
pyamqp/rabbit/core/base_connector.py
